msprites2/__init__.py
msprites2/audio_transcription.py
msprites2/enhancers.py
msprites2/montage_sprites.py
msprites2/parallel_extractor.py
msprites2/settings.py
msprites2/visual_analysis.py
msprites2-0.13.0.dist-info/METADATA
msprites2-0.13.0.dist-info/WHEEL
msprites2-0.13.0.dist-info/licenses/LICENSE
msprites2-0.13.0.dist-info/RECORD
