Metadata-Version: 2.4
Name: msprites2
Version: 0.13.0
Summary: Create thumbnail spritesheets, generate AI-powered captions & visual descriptions with enhancement pipeline, and process video frames with multi-format output
Project-URL: Homepage, https://github.com/rsp2k/msprites2
Project-URL: Repository, https://github.com/rsp2k/msprites2.git
Project-URL: Issues, https://github.com/rsp2k/msprites2/issues
Project-URL: Changelog, https://github.com/rsp2k/msprites2/releases
Author-email: Ryan Malloy <ryan@supported.systems>
Maintainer-email: Ryan Malloy <ryan@supported.systems>
License: MIT License
License-File: LICENSE
Keywords: accessibility,ai,captions,ffmpeg,imagemagick,llava,ollama,sprites,subtitles,thumbnails,transcription,video,vision,webvtt,whisper
Classifier: Development Status :: 4 - Beta
Classifier: Intended Audience :: Developers
Classifier: License :: OSI Approved :: MIT License
Classifier: Operating System :: OS Independent
Classifier: Programming Language :: Python :: 3
Classifier: Programming Language :: Python :: 3.9
Classifier: Programming Language :: Python :: 3.10
Classifier: Programming Language :: Python :: 3.11
Classifier: Programming Language :: Python :: 3.12
Classifier: Programming Language :: Python :: 3.13
Classifier: Topic :: Multimedia :: Video
Classifier: Topic :: Software Development :: Libraries :: Python Modules
Requires-Python: >=3.9
Requires-Dist: ffmpeg-python>=0.2.0
Provides-Extra: ai
Requires-Dist: faster-whisper>=1.2.0; extra == 'ai'
Requires-Dist: ollama>=0.6.0; extra == 'ai'
Provides-Extra: all
Requires-Dist: faster-whisper>=1.2.0; extra == 'all'
Requires-Dist: ollama>=0.6.0; extra == 'all'
Provides-Extra: dev
Requires-Dist: pytest-cov>=4.0; extra == 'dev'
Requires-Dist: pytest>=7.0; extra == 'dev'
Requires-Dist: ruff>=0.1.0; extra == 'dev'
Provides-Extra: test
Requires-Dist: pytest-cov>=4.0; extra == 'test'
Requires-Dist: pytest>=7.0; extra == 'test'
Provides-Extra: transcription
Requires-Dist: faster-whisper>=1.2.0; extra == 'transcription'
Provides-Extra: vision
Requires-Dist: ollama>=0.6.0; extra == 'vision'
